LinghunYongsheng/Dockerfile
LinghunYongsheng/README.md
LinghunYongsheng/__init__.py
LinghunYongsheng/__main__.py
LinghunYongsheng/file.epub
LinghunYongsheng/index.html
LinghunYongsheng/css/__init__.py
LinghunYongsheng/css/annotations.css
LinghunYongsheng/css/main.css
LinghunYongsheng/css/normalize.css
LinghunYongsheng/css/popup.css
LinghunYongsheng/font/__init__.py
LinghunYongsheng/font/fontello.eot
LinghunYongsheng/font/fontello.svg
LinghunYongsheng/font/fontello.ttf
LinghunYongsheng/font/fontello.woff
LinghunYongsheng/img/__init__.py
LinghunYongsheng/img/annotator-glyph-sprite.png
LinghunYongsheng/img/annotator-icon-sprite.png
LinghunYongsheng/img/apple-touch-icon.png
LinghunYongsheng/img/cancelfullscreen.png
LinghunYongsheng/img/close.png
LinghunYongsheng/img/fullscreen.png
LinghunYongsheng/img/loader.gif
LinghunYongsheng/img/menu-icon.png
LinghunYongsheng/img/save.png
LinghunYongsheng/img/saved.png
LinghunYongsheng/img/settings-s.png
LinghunYongsheng/img/settings.png
LinghunYongsheng/img/star.png
LinghunYongsheng/js/__init__.py
LinghunYongsheng/js/epub.js
LinghunYongsheng/js/epub.min.js
LinghunYongsheng/js/epub.min.map
LinghunYongsheng/js/hooks.min.js
LinghunYongsheng/js/hooks.min.map
LinghunYongsheng/js/reader.js
LinghunYongsheng/js/reader.js.map
LinghunYongsheng/js/reader.min.js
LinghunYongsheng/js/reader.min.map
LinghunYongsheng/js/hooks/__init__.py
LinghunYongsheng/js/hooks/extensions/__init__.py
LinghunYongsheng/js/hooks/extensions/highlight.js
LinghunYongsheng/js/libs/__init__.py
LinghunYongsheng/js/libs/jquery.min.js
LinghunYongsheng/js/libs/localforage.min.js
LinghunYongsheng/js/libs/screenfull.js
LinghunYongsheng/js/libs/screenfull.min.js
LinghunYongsheng/js/libs/zip.min.js
LinghunYongsheng/js/plugins/__init__.py
LinghunYongsheng/js/plugins/hypothesis.js
LinghunYongsheng/js/plugins/search.js
linghun_yongsheng-2022.10.9.1.dist-info/METADATA
linghun_yongsheng-2022.10.9.1.dist-info/WHEEL
linghun_yongsheng-2022.10.9.1.dist-info/entry_points.txt
linghun_yongsheng-2022.10.9.1.dist-info/top_level.txt
linghun_yongsheng-2022.10.9.1.dist-info/RECORD
